pydocstringformatter/__init__.py
pydocstringformatter/__main__.py
pydocstringformatter/run.py
pydocstringformatter/_configuration/__init__.py
pydocstringformatter/_configuration/arguments_manager.py
pydocstringformatter/_configuration/boolean_option_action.py
pydocstringformatter/_configuration/command_line_parsing.py
pydocstringformatter/_configuration/formatter_options.py
pydocstringformatter/_configuration/toml_parsing.py
pydocstringformatter/_configuration/validators.py
pydocstringformatter/_formatting/__init__.py
pydocstringformatter/_formatting/_utils.py
pydocstringformatter/_formatting/base.py
pydocstringformatter/_formatting/formatters_default.py
pydocstringformatter/_formatting/formatters_numpydoc.py
pydocstringformatter/_formatting/formatters_pep257.py
pydocstringformatter/_testutils/__init__.py
pydocstringformatter/_testutils/example_formatters.py
pydocstringformatter/_testutils/primer/__init__.py
pydocstringformatter/_testutils/primer/const.py
pydocstringformatter/_testutils/primer/packages.py
pydocstringformatter/_testutils/primer/primer.py
pydocstringformatter/_utils/__init__.py
pydocstringformatter/_utils/exceptions.py
pydocstringformatter/_utils/file_diference.py
pydocstringformatter/_utils/find_docstrings.py
pydocstringformatter/_utils/find_python_file.py
pydocstringformatter/_utils/issue_template.py
pydocstringformatter/_utils/output.py
pydocstringformatter-0.7.5.dist-info/licenses/LICENSE
pydocstringformatter-0.7.5.dist-info/METADATA
pydocstringformatter-0.7.5.dist-info/WHEEL
pydocstringformatter-0.7.5.dist-info/entry_points.txt
pydocstringformatter-0.7.5.dist-info/top_level.txt
pydocstringformatter-0.7.5.dist-info/RECORD
