Metadata-Version: 2.4
Name: pydocstringformatter
Version: 0.7.5
Summary: A tool to automatically format Python docstrings that tries to follow recommendations from PEP 8 and PEP 257.
Author-email: Daniël van Noord <13665637+DanielNoord@users.noreply.github.com>
License: MIT
Project-URL: Repository, https://github.com/DanielNoord/pydocstringformatter
Project-URL: Releases, https://github.com/DanielNoord/pydocstringformatter/releases
Project-URL: Bug Tracker, https://github.com/DanielNoord/pydocstringformatter/issues
Keywords: python,docstring,format
Classifier: Development Status :: 5 - Production/Stable
Classifier: Environment :: Console
Classifier: Intended Audience :: Developers
Classifier: License :: OSI Approved :: MIT License
Classifier: Operating System :: OS Independent
Classifier: Programming Language :: Python
Classifier: Programming Language :: Python :: 3
Classifier: Programming Language :: Python :: 3 :: Only
Classifier: Programming Language :: Python :: 3.8
Classifier: Programming Language :: Python :: 3.9
Classifier: Programming Language :: Python :: 3.10
Classifier: Programming Language :: Python :: 3.11
Classifier: Programming Language :: Python :: 3.12
Classifier: Programming Language :: Python :: 3.13
Classifier: Programming Language :: Python :: 3.14
Classifier: Programming Language :: Python :: 3.15
Classifier: Programming Language :: Python :: Implementation :: CPython
Classifier: Topic :: Software Development :: Quality Assurance
Requires-Python: >=3.8
License-File: LICENSE
Requires-Dist: tomli>=1.1.0; python_version < "3.11"
Dynamic: license-file
